tetrayau/__init__.py
tetrayau/hbb_blockchain.py
tetrayau/ledger.py
tetrayau/qidl_encrypt.py
tetrayau/rth.py
tetrayau/tke.py
tetrayau-2.0.0.dist-info/licenses/LICENSE
tetrayau-2.0.0.dist-info/METADATA
tetrayau-2.0.0.dist-info/WHEEL
tetrayau-2.0.0.dist-info/top_level.txt
tetrayau-2.0.0.dist-info/RECORD
