Metadata-Version: 2.4
Name: tetrayau
Version: 2.0.0
Summary: TetraYau: Hyperdimensional Sovereign Cryptography Suite
Home-page: https://github.com/Abraxas618/TetraYau
Author: Michael Tass MacDonald (Abraxas618)
License: Apache-2.0
Classifier: Development Status :: 5 - Production/Stable
Classifier: License :: OSI Approved :: Apache Software License
Classifier: Programming Language :: Python :: 3.8
Classifier: Programming Language :: Python :: 3.9
Classifier: Programming Language :: Python :: 3.10
Classifier: Programming Language :: Python :: 3.11
Requires-Python: >=3.8
License-File: LICENSE
Dynamic: author
Dynamic: classifier
Dynamic: description
Dynamic: description-content-type
Dynamic: home-page
Dynamic: license
Dynamic: license-file
Dynamic: requires-python
Dynamic: summary
